gitlab_label_mover/__init__.py
gitlab_label_mover/cli.py
gitlab_label_mover/config.py
gitlab_label_mover/core.py
gitlab_label_mover/gitlab_api.py
gitlab_label_mover/label_management.py
gitlab_label_mover/main.py
gitlab_label_mover/resource_management.py
gitlab_label_mover/utils/__init__.py
gitlab_label_mover/visualization.py
gitlab_label_mover-0.1.13.dist-info/LICENSE
gitlab_label_mover-0.1.13.dist-info/METADATA
gitlab_label_mover-0.1.13.dist-info/WHEEL
gitlab_label_mover-0.1.13.dist-info/entry_points.txt
gitlab_label_mover-0.1.13.dist-info/RECORD
