Metadata-Version: 2.3
Name: gitlab-label-mover
Version: 0.1.13
Summary: Tool to migrate labels from a GitLab project to a group
License: MIT
Keywords: gitlab,labels,migration,devops,automation
Author: Nikolai von Krusenstiern
Author-email: gitlab.com@yoso.de
Maintainer: Nikolai von Krusenstiern
Maintainer-email: gitlab.com@yoso.de
Requires-Python: >=3.9
Classifier: Development Status :: 4 - Beta
Classifier: Environment :: Console
Classifier: Intended Audience :: Developers
Classifier: Intended Audience :: System Administrators
Classifier: License :: OSI Approved :: MIT License
Classifier: Programming Language :: Python :: 3
Classifier: Programming Language :: Python :: 3.9
Classifier: Programming Language :: Python :: 3.10
Classifier: Programming Language :: Python :: 3.11
Classifier: Topic :: Software Development :: Version Control :: Git
Classifier: Topic :: Utilities
Requires-Dist: platformdirs (>=3.0.0)
Requires-Dist: python-dotenv (>=1.0.0)
Requires-Dist: python-gitlab (>=5.6.0,<6.0.0)
Project-URL: Documentation, https://gitlab.com/python-tools4/git/gitlab-label-mover
Project-URL: Homepage, https://gitlab.com/python-tools4/git/gitlab-label-mover
Project-URL: PyPI, https://pypi.org/project/gitlab-label-mover/
Project-URL: Repository, https://gitlab.com/python-tools4/git/gitlab-label-mover
